discopilot/__init__.py
discopilot-0.1.7.dist-info/METADATA
discopilot-0.1.7.dist-info/WHEEL
discopilot-0.1.7.dist-info/entry_points.txt
discopilot-0.1.7.dist-info/top_level.txt
discopilot-0.1.7.dist-info/RECORD
