Metadata-Version: 2.4
Name: discopilot
Version: 0.1.7
Summary: A Discord bot that cross-posts to social media platforms
Author-email: tengfei <tengfei@twinko.ai>
License-Expression: Apache-2.0
Project-URL: Homepage, https://github.com/twinko-ai/discopilot
Project-URL: Bug Tracker, https://github.com/twinko-ai/discopilot/issues
Classifier: Programming Language :: Python :: 3
Classifier: Programming Language :: Python :: 3.9
Classifier: Programming Language :: Python :: 3.10
Classifier: Programming Language :: Python :: 3.11
Classifier: Programming Language :: Python :: 3.12
Classifier: Operating System :: OS Independent
Requires-Python: >=3.9
Requires-Dist: discord.py>=2.0.0
Requires-Dist: tweepy>=4.14.0
Requires-Dist: pyyaml>=6.0
Requires-Dist: python-dotenv>=1.0.0
Provides-Extra: dev
Requires-Dist: pytest>=7.0.0; extra == "dev"
Requires-Dist: pytest-cov>=4.0.0; extra == "dev"
Requires-Dist: pytest-asyncio>=0.21.0; extra == "dev"
Requires-Dist: black>=23.0.0; extra == "dev"
Requires-Dist: isort>=5.0.0; extra == "dev"
Requires-Dist: flake8>=6.0.0; extra == "dev"
Requires-Dist: flake8-pyproject>=1.2.3; extra == "dev"
